excellent_quote/__init__.py
excellent_quote/cli.py
excellent_quote/loader.py
excellent_quote/quotes.csv
excellent_quote-0.1.0.dist-info/METADATA
excellent_quote-0.1.0.dist-info/WHEEL
excellent_quote-0.1.0.dist-info/entry_points.txt
excellent_quote-0.1.0.dist-info/top_level.txt
excellent_quote-0.1.0.dist-info/RECORD
