Metadata-Version: 2.4
Name: excellent_quote
Version: 0.1.0
Summary: Tiny CLI that prints random Kevin Kelly quotes
License: MIT
Requires-Python: >=3.8
Requires-Dist: click
